bblocks/datacommons_tools/__init__.py
bblocks/datacommons_tools/__main__.py
bblocks/datacommons_tools/cli/__init__.py
bblocks/datacommons_tools/cli/common.py
bblocks/datacommons_tools/cli/csv2mcf.py
bblocks/datacommons_tools/cli/data_load.py
bblocks/datacommons_tools/cli/data_load_pipeline.py
bblocks/datacommons_tools/cli/main.py
bblocks/datacommons_tools/cli/redeploy.py
bblocks/datacommons_tools/cli/upload.py
bblocks/datacommons_tools/custom_data/__init__.py
bblocks/datacommons_tools/custom_data/config_utils.py
bblocks/datacommons_tools/custom_data/data_management.py
bblocks/datacommons_tools/custom_data/models/__init__.py
bblocks/datacommons_tools/custom_data/models/common.py
bblocks/datacommons_tools/custom_data/models/config_file.py
bblocks/datacommons_tools/custom_data/models/data_files.py
bblocks/datacommons_tools/custom_data/models/mcf.py
bblocks/datacommons_tools/custom_data/models/sources.py
bblocks/datacommons_tools/custom_data/models/stat_vars.py
bblocks/datacommons_tools/custom_data/models/topics.py
bblocks/datacommons_tools/custom_data/schema_tools.py
bblocks/datacommons_tools/gcp_utilities/__init__.py
bblocks/datacommons_tools/gcp_utilities/clients.py
bblocks/datacommons_tools/gcp_utilities/jobs.py
bblocks/datacommons_tools/gcp_utilities/pipeline.py
bblocks/datacommons_tools/gcp_utilities/settings.py
bblocks/datacommons_tools/gcp_utilities/storage.py
bblocks/datacommons_tools/logger.py
bblocks_datacommons_tools-0.0.9.dist-info/METADATA
bblocks_datacommons_tools-0.0.9.dist-info/WHEEL
bblocks_datacommons_tools-0.0.9.dist-info/entry_points.txt
bblocks_datacommons_tools-0.0.9.dist-info/licenses/LICENSE
bblocks_datacommons_tools-0.0.9.dist-info/RECORD
