Metadata-Version: 2.4
Name: bblocks-datacommons-tools
Version: 0.0.9
Summary: Tools to work with Data Commons. Part of the bblocks projects.
License: MIT
License-File: LICENSE
Author: ONE Campaign
Requires-Python: >=3.11
Classifier: License :: OSI Approved :: MIT License
Classifier: Programming Language :: Python :: 3
Classifier: Programming Language :: Python :: 3.11
Classifier: Programming Language :: Python :: 3.12
Classifier: Programming Language :: Python :: 3.13
Classifier: Programming Language :: Python :: 3.14
Requires-Dist: google-cloud-run (>=0.10.17,<0.11.0)
Requires-Dist: google-cloud-storage (>=3.1.0,<4.0.0)
Requires-Dist: pandas (>=2.2.3,<3.0.0)
Requires-Dist: pydantic (>=2.11.3,<3.0.0)
Requires-Dist: pydantic-settings (>=2.9.1,<3.0.0)
